{
    "uid": "d33213ac-d866-463a-a270-f4318d725eaf",
    "name": "47_ExtraTrees",
    "preprocessing": [
        {
            "categorical": [
                {
                    "convert_method": "categorical_to_int",
                    "convert_params": {
                        "Type": {
                            "H": 0,
                            "L": 1,
                            "M": 2
                        }
                    },
                    "columns": [
                        "Type"
                    ]
                }
            ],
            "categorical_y": {
                "Heat_Dissipation_Failure": 0,
                "No_Failure": 1,
                "Overstrain_Failure": 2,
                "Power_Failure": 3,
                "Tool_Wear_Failure": 4
            },
            "ml_task": "multiclass_classification",
            "params": {
                "columns_preprocessing": {
                    "Type": [
                        "categorical_to_int"
                    ]
                },
                "target_preprocessing": [
                    "na_exclude",
                    "categorical_to_int"
                ],
                "ml_task": "multiclass_classification"
            }
        },
        {
            "categorical": [
                {
                    "convert_method": "categorical_to_int",
                    "convert_params": {
                        "Type": {
                            "H": 0,
                            "L": 1,
                            "M": 2
                        }
                    },
                    "columns": [
                        "Type"
                    ]
                }
            ],
            "categorical_y": {
                "Heat_Dissipation_Failure": 0,
                "No_Failure": 1,
                "Overstrain_Failure": 2,
                "Power_Failure": 3,
                "Tool_Wear_Failure": 4
            },
            "ml_task": "multiclass_classification",
            "params": {
                "columns_preprocessing": {
                    "Type": [
                        "categorical_to_int"
                    ]
                },
                "target_preprocessing": [
                    "na_exclude",
                    "categorical_to_int"
                ],
                "ml_task": "multiclass_classification"
            }
        },
        {
            "categorical": [
                {
                    "convert_method": "categorical_to_int",
                    "convert_params": {
                        "Type": {
                            "H": 0,
                            "L": 1,
                            "M": 2
                        }
                    },
                    "columns": [
                        "Type"
                    ]
                }
            ],
            "categorical_y": {
                "Heat_Dissipation_Failure": 0,
                "No_Failure": 1,
                "Overstrain_Failure": 2,
                "Power_Failure": 3,
                "Tool_Wear_Failure": 4
            },
            "ml_task": "multiclass_classification",
            "params": {
                "columns_preprocessing": {
                    "Type": [
                        "categorical_to_int"
                    ]
                },
                "target_preprocessing": [
                    "na_exclude",
                    "categorical_to_int"
                ],
                "ml_task": "multiclass_classification"
            }
        },
        {
            "categorical": [
                {
                    "convert_method": "categorical_to_int",
                    "convert_params": {
                        "Type": {
                            "H": 0,
                            "L": 1,
                            "M": 2
                        }
                    },
                    "columns": [
                        "Type"
                    ]
                }
            ],
            "categorical_y": {
                "Heat_Dissipation_Failure": 0,
                "No_Failure": 1,
                "Overstrain_Failure": 2,
                "Power_Failure": 3,
                "Tool_Wear_Failure": 4
            },
            "ml_task": "multiclass_classification",
            "params": {
                "columns_preprocessing": {
                    "Type": [
                        "categorical_to_int"
                    ]
                },
                "target_preprocessing": [
                    "na_exclude",
                    "categorical_to_int"
                ],
                "ml_task": "multiclass_classification"
            }
        },
        {
            "categorical": [
                {
                    "convert_method": "categorical_to_int",
                    "convert_params": {
                        "Type": {
                            "H": 0,
                            "L": 1,
                            "M": 2
                        }
                    },
                    "columns": [
                        "Type"
                    ]
                }
            ],
            "categorical_y": {
                "Heat_Dissipation_Failure": 0,
                "No_Failure": 1,
                "Overstrain_Failure": 2,
                "Power_Failure": 3,
                "Tool_Wear_Failure": 4
            },
            "ml_task": "multiclass_classification",
            "params": {
                "columns_preprocessing": {
                    "Type": [
                        "categorical_to_int"
                    ]
                },
                "target_preprocessing": [
                    "na_exclude",
                    "categorical_to_int"
                ],
                "ml_task": "multiclass_classification"
            }
        }
    ],
    "learners": [
        {
            "library_version": "1.6.1",
            "algorithm_name": "Extra Trees Classifier",
            "algorithm_short_name": "Extra Trees",
            "uid": "beab8c66-02ad-4dd4-a4a7-9a26e2ad31a0",
            "params": {
                "model_type": "Extra Trees",
                "ml_task": "multiclass_classification",
                "n_jobs": -1,
                "seed": 47,
                "criterion": "gini",
                "max_features": 0.7,
                "min_samples_split": 50,
                "max_depth": 3,
                "eval_metric_name": "logloss",
                "num_class": 5,
                "explain_level": 2
            },
            "name": "learner_fold_0"
        },
        {
            "library_version": "1.6.1",
            "algorithm_name": "Extra Trees Classifier",
            "algorithm_short_name": "Extra Trees",
            "uid": "cb37e8e8-17b3-49f5-9f94-eb6d27a05091",
            "params": {
                "model_type": "Extra Trees",
                "ml_task": "multiclass_classification",
                "n_jobs": -1,
                "seed": 47,
                "criterion": "gini",
                "max_features": 0.7,
                "min_samples_split": 50,
                "max_depth": 3,
                "eval_metric_name": "logloss",
                "num_class": 5,
                "explain_level": 2
            },
            "name": "learner_fold_1"
        },
        {
            "library_version": "1.6.1",
            "algorithm_name": "Extra Trees Classifier",
            "algorithm_short_name": "Extra Trees",
            "uid": "050201cc-f3cc-49f4-aa13-7bc303c680d8",
            "params": {
                "model_type": "Extra Trees",
                "ml_task": "multiclass_classification",
                "n_jobs": -1,
                "seed": 47,
                "criterion": "gini",
                "max_features": 0.7,
                "min_samples_split": 50,
                "max_depth": 3,
                "eval_metric_name": "logloss",
                "num_class": 5,
                "explain_level": 2
            },
            "name": "learner_fold_2"
        },
        {
            "library_version": "1.6.1",
            "algorithm_name": "Extra Trees Classifier",
            "algorithm_short_name": "Extra Trees",
            "uid": "7fe01322-b264-474d-9460-227651d4978f",
            "params": {
                "model_type": "Extra Trees",
                "ml_task": "multiclass_classification",
                "n_jobs": -1,
                "seed": 47,
                "criterion": "gini",
                "max_features": 0.7,
                "min_samples_split": 50,
                "max_depth": 3,
                "eval_metric_name": "logloss",
                "num_class": 5,
                "explain_level": 2
            },
            "name": "learner_fold_3"
        },
        {
            "library_version": "1.6.1",
            "algorithm_name": "Extra Trees Classifier",
            "algorithm_short_name": "Extra Trees",
            "uid": "d3b276c7-e969-48f5-b2b0-e0c3ed5f667b",
            "params": {
                "model_type": "Extra Trees",
                "ml_task": "multiclass_classification",
                "n_jobs": -1,
                "seed": 47,
                "criterion": "gini",
                "max_features": 0.7,
                "min_samples_split": 50,
                "max_depth": 3,
                "eval_metric_name": "logloss",
                "num_class": 5,
                "explain_level": 2
            },
            "name": "learner_fold_4"
        }
    ],
    "params": {
        "additional": {
            "trees_in_step": 100,
            "max_steps": 50,
            "early_stopping_rounds": 50,
            "max_rows_limit": null,
            "max_cols_limit": null
        },
        "preprocessing": {
            "columns_preprocessing": {
                "Type": [
                    "categorical_to_int"
                ]
            },
            "target_preprocessing": [
                "na_exclude",
                "categorical_to_int"
            ],
            "ml_task": "multiclass_classification"
        },
        "validation_strategy": {
            "validation_type": "kfold",
            "k_folds": 5,
            "shuffle": true,
            "stratify": true,
            "random_seed": 42,
            "X_path": "AutoML_AI4I_Multiclass/X.data",
            "y_path": "AutoML_AI4I_Multiclass/y.data",
            "results_path": "AutoML_AI4I_Multiclass"
        },
        "learner": {
            "model_type": "Extra Trees",
            "ml_task": "multiclass_classification",
            "n_jobs": -1,
            "seed": 47,
            "criterion": "gini",
            "max_features": 0.7,
            "min_samples_split": 50,
            "max_depth": 3,
            "eval_metric_name": "logloss",
            "num_class": 5,
            "explain_level": 2
        },
        "automl_random_state": 42,
        "ml_task": "multiclass_classification",
        "explain_level": 2,
        "name": "47_ExtraTrees",
        "status": "initialized",
        "final_loss": null,
        "train_time": null,
        "data_type": "original",
        "max_time_for_learner": 60
    },
    "saved": [
        "47_ExtraTrees/learner_fold_0.extra_trees",
        "47_ExtraTrees/learner_fold_1.extra_trees",
        "47_ExtraTrees/learner_fold_2.extra_trees",
        "47_ExtraTrees/learner_fold_3.extra_trees",
        "47_ExtraTrees/learner_fold_4.extra_trees"
    ],
    "predictions_fname": "47_ExtraTrees/predictions_out_of_folds.csv",
    "metric_name": "logloss",
    "final_loss": "0.12296847033873994",
    "train_time": 18.794128894805908,
    "is_stacked": false,
    "joblib_version": "1.5.3"
}