{
    "uid": "468726cf-c8a0-4afe-b1c8-06ad346758a3",
    "name": "55_CatBoost",
    "preprocessing": [
        {
            "scale_y": {
                "scale": [
                    16.065133797995042
                ],
                "mean": [
                    35.83677083333334
                ],
                "var": [
                    258.0885239474826
                ],
                "n_samples_seen": 576,
                "n_features_in": 1,
                "columns": [
                    "target"
                ],
                "scale_method": "scale_normal"
            },
            "ml_task": "regression",
            "params": {
                "columns_preprocessing": {},
                "target_preprocessing": [
                    "na_exclude",
                    "scale_normal"
                ],
                "ml_task": "regression"
            }
        },
        {
            "scale_y": {
                "scale": [
                    16.32467381921671
                ],
                "mean": [
                    35.732708333333335
                ],
                "var": [
                    266.49497530381944
                ],
                "n_samples_seen": 576,
                "n_features_in": 1,
                "columns": [
                    "target"
                ],
                "scale_method": "scale_normal"
            },
            "ml_task": "regression",
            "params": {
                "columns_preprocessing": {},
                "target_preprocessing": [
                    "na_exclude",
                    "scale_normal"
                ],
                "ml_task": "regression"
            }
        },
        {
            "scale_y": {
                "scale": [
                    16.846179028420384
                ],
                "mean": [
                    36.27475694444444
                ],
                "var": [
                    283.7937478575907
                ],
                "n_samples_seen": 576,
                "n_features_in": 1,
                "columns": [
                    "target"
                ],
                "scale_method": "scale_normal"
            },
            "ml_task": "regression",
            "params": {
                "columns_preprocessing": {},
                "target_preprocessing": [
                    "na_exclude",
                    "scale_normal"
                ],
                "ml_task": "regression"
            }
        },
        {
            "scale_y": {
                "scale": [
                    16.540091162165027
                ],
                "mean": [
                    35.93711805555555
                ],
                "var": [
                    273.57461565272956
                ],
                "n_samples_seen": 576,
                "n_features_in": 1,
                "columns": [
                    "target"
                ],
                "scale_method": "scale_normal"
            },
            "ml_task": "regression",
            "params": {
                "columns_preprocessing": {},
                "target_preprocessing": [
                    "na_exclude",
                    "scale_normal"
                ],
                "ml_task": "regression"
            }
        },
        {
            "scale_y": {
                "scale": [
                    16.59640991093148
                ],
                "mean": [
                    36.22142361111111
                ],
                "var": [
                    275.4408219316647
                ],
                "n_samples_seen": 576,
                "n_features_in": 1,
                "columns": [
                    "target"
                ],
                "scale_method": "scale_normal"
            },
            "ml_task": "regression",
            "params": {
                "columns_preprocessing": {},
                "target_preprocessing": [
                    "na_exclude",
                    "scale_normal"
                ],
                "ml_task": "regression"
            }
        }
    ],
    "learners": [
        {
            "library_version": "1.2.10",
            "algorithm_name": "CatBoost",
            "algorithm_short_name": "CatBoost",
            "uid": "80033e9a-8674-4d4f-9246-6ce0aa53baf1",
            "params": {
                "model_type": "CatBoost",
                "ml_task": "regression",
                "n_jobs": -1,
                "seed": 43,
                "learning_rate": 0.1,
                "depth": 6,
                "rsm": 0.8,
                "loss_function": "RMSE",
                "eval_metric": "RMSE",
                "explain_level": 1
            },
            "name": "learner_fold_0",
            "best_ntree_limit": 405
        },
        {
            "library_version": "1.2.10",
            "algorithm_name": "CatBoost",
            "algorithm_short_name": "CatBoost",
            "uid": "15622442-0070-4492-97ce-05e05aa6bd1b",
            "params": {
                "model_type": "CatBoost",
                "ml_task": "regression",
                "n_jobs": -1,
                "seed": 43,
                "learning_rate": 0.1,
                "depth": 6,
                "rsm": 0.8,
                "loss_function": "RMSE",
                "eval_metric": "RMSE",
                "explain_level": 1
            },
            "name": "learner_fold_1",
            "best_ntree_limit": 509
        },
        {
            "library_version": "1.2.10",
            "algorithm_name": "CatBoost",
            "algorithm_short_name": "CatBoost",
            "uid": "34cfdf02-2692-4a15-8709-d87a02058787",
            "params": {
                "model_type": "CatBoost",
                "ml_task": "regression",
                "n_jobs": -1,
                "seed": 43,
                "learning_rate": 0.1,
                "depth": 6,
                "rsm": 0.8,
                "loss_function": "RMSE",
                "eval_metric": "RMSE",
                "explain_level": 1
            },
            "name": "learner_fold_2",
            "best_ntree_limit": 957
        },
        {
            "library_version": "1.2.10",
            "algorithm_name": "CatBoost",
            "algorithm_short_name": "CatBoost",
            "uid": "15e57943-6fd1-4de6-8a20-c03c6d902574",
            "params": {
                "model_type": "CatBoost",
                "ml_task": "regression",
                "n_jobs": -1,
                "seed": 43,
                "learning_rate": 0.1,
                "depth": 6,
                "rsm": 0.8,
                "loss_function": "RMSE",
                "eval_metric": "RMSE",
                "explain_level": 1
            },
            "name": "learner_fold_3",
            "best_ntree_limit": 277
        },
        {
            "library_version": "1.2.10",
            "algorithm_name": "CatBoost",
            "algorithm_short_name": "CatBoost",
            "uid": "734e60ba-8253-4014-9b08-a5bdb470bb69",
            "params": {
                "model_type": "CatBoost",
                "ml_task": "regression",
                "n_jobs": -1,
                "seed": 43,
                "learning_rate": 0.1,
                "depth": 6,
                "rsm": 0.8,
                "loss_function": "RMSE",
                "eval_metric": "RMSE",
                "explain_level": 1
            },
            "name": "learner_fold_4",
            "best_ntree_limit": 343
        }
    ],
    "params": {
        "additional": {
            "max_rounds": 10000,
            "early_stopping_rounds": 50,
            "max_rows_limit": null,
            "max_cols_limit": null
        },
        "preprocessing": {
            "columns_preprocessing": {},
            "target_preprocessing": [
                "na_exclude",
                "scale_normal"
            ],
            "ml_task": "regression"
        },
        "validation_strategy": {
            "validation_type": "kfold",
            "k_folds": 5,
            "shuffle": true,
            "random_seed": 42,
            "X_path": "models/AutoML_Concrete_Strength/X.data",
            "y_path": "models/AutoML_Concrete_Strength/y.data",
            "results_path": "models/AutoML_Concrete_Strength"
        },
        "learner": {
            "model_type": "CatBoost",
            "ml_task": "regression",
            "n_jobs": -1,
            "seed": 43,
            "learning_rate": 0.1,
            "depth": 6,
            "rsm": 0.8,
            "loss_function": "RMSE",
            "eval_metric": "RMSE",
            "explain_level": 1
        },
        "automl_random_state": 42,
        "ml_task": "regression",
        "explain_level": 1,
        "name": "55_CatBoost",
        "status": "initialized",
        "final_loss": null,
        "train_time": null,
        "data_type": "original",
        "max_time_for_learner": 60
    },
    "saved": [
        "55_CatBoost/learner_fold_0.catboost",
        "55_CatBoost/learner_fold_1.catboost",
        "55_CatBoost/learner_fold_2.catboost",
        "55_CatBoost/learner_fold_3.catboost",
        "55_CatBoost/learner_fold_4.catboost"
    ],
    "predictions_fname": "55_CatBoost/predictions_out_of_folds.csv",
    "metric_name": "rmse",
    "final_loss": "4.603154421025298",
    "train_time": 6.975522041320801,
    "is_stacked": false,
    "joblib_version": "1.5.3"
}