{
    "uid": "2250ae86-42a0-4ad6-ae2f-0e6ee5798e6f",
    "name": "76_CatBoost",
    "preprocessing": [
        {
            "scale_y": {
                "scale": [
                    16.065133797995042
                ],
                "mean": [
                    35.83677083333334
                ],
                "var": [
                    258.0885239474826
                ],
                "n_samples_seen": 576,
                "n_features_in": 1,
                "columns": [
                    "target"
                ],
                "scale_method": "scale_normal"
            },
            "ml_task": "regression",
            "params": {
                "columns_preprocessing": {},
                "target_preprocessing": [
                    "na_exclude",
                    "scale_normal"
                ],
                "ml_task": "regression"
            }
        },
        {
            "scale_y": {
                "scale": [
                    16.32467381921671
                ],
                "mean": [
                    35.732708333333335
                ],
                "var": [
                    266.49497530381944
                ],
                "n_samples_seen": 576,
                "n_features_in": 1,
                "columns": [
                    "target"
                ],
                "scale_method": "scale_normal"
            },
            "ml_task": "regression",
            "params": {
                "columns_preprocessing": {},
                "target_preprocessing": [
                    "na_exclude",
                    "scale_normal"
                ],
                "ml_task": "regression"
            }
        },
        {
            "scale_y": {
                "scale": [
                    16.846179028420384
                ],
                "mean": [
                    36.27475694444444
                ],
                "var": [
                    283.7937478575907
                ],
                "n_samples_seen": 576,
                "n_features_in": 1,
                "columns": [
                    "target"
                ],
                "scale_method": "scale_normal"
            },
            "ml_task": "regression",
            "params": {
                "columns_preprocessing": {},
                "target_preprocessing": [
                    "na_exclude",
                    "scale_normal"
                ],
                "ml_task": "regression"
            }
        },
        {
            "scale_y": {
                "scale": [
                    16.540091162165027
                ],
                "mean": [
                    35.93711805555555
                ],
                "var": [
                    273.57461565272956
                ],
                "n_samples_seen": 576,
                "n_features_in": 1,
                "columns": [
                    "target"
                ],
                "scale_method": "scale_normal"
            },
            "ml_task": "regression",
            "params": {
                "columns_preprocessing": {},
                "target_preprocessing": [
                    "na_exclude",
                    "scale_normal"
                ],
                "ml_task": "regression"
            }
        },
        {
            "scale_y": {
                "scale": [
                    16.59640991093148
                ],
                "mean": [
                    36.22142361111111
                ],
                "var": [
                    275.4408219316647
                ],
                "n_samples_seen": 576,
                "n_features_in": 1,
                "columns": [
                    "target"
                ],
                "scale_method": "scale_normal"
            },
            "ml_task": "regression",
            "params": {
                "columns_preprocessing": {},
                "target_preprocessing": [
                    "na_exclude",
                    "scale_normal"
                ],
                "ml_task": "regression"
            }
        }
    ],
    "learners": [
        {
            "library_version": "1.2.10",
            "algorithm_name": "CatBoost",
            "algorithm_short_name": "CatBoost",
            "uid": "8f4e1928-79b8-4e87-8b51-ba86153aee0c",
            "params": {
                "model_type": "CatBoost",
                "ml_task": "regression",
                "n_jobs": -1,
                "seed": 43,
                "learning_rate": 0.1,
                "depth": 5,
                "rsm": 0.8,
                "loss_function": "RMSE",
                "eval_metric": "RMSE",
                "explain_level": 1
            },
            "name": "learner_fold_0",
            "best_ntree_limit": 399
        },
        {
            "library_version": "1.2.10",
            "algorithm_name": "CatBoost",
            "algorithm_short_name": "CatBoost",
            "uid": "a50a1df9-dddf-4865-ad12-32820ea1bc2a",
            "params": {
                "model_type": "CatBoost",
                "ml_task": "regression",
                "n_jobs": -1,
                "seed": 43,
                "learning_rate": 0.1,
                "depth": 5,
                "rsm": 0.8,
                "loss_function": "RMSE",
                "eval_metric": "RMSE",
                "explain_level": 1
            },
            "name": "learner_fold_1",
            "best_ntree_limit": 391
        },
        {
            "library_version": "1.2.10",
            "algorithm_name": "CatBoost",
            "algorithm_short_name": "CatBoost",
            "uid": "c3c78339-835c-4e5f-adab-3d251a8b3dcb",
            "params": {
                "model_type": "CatBoost",
                "ml_task": "regression",
                "n_jobs": -1,
                "seed": 43,
                "learning_rate": 0.1,
                "depth": 5,
                "rsm": 0.8,
                "loss_function": "RMSE",
                "eval_metric": "RMSE",
                "explain_level": 1
            },
            "name": "learner_fold_2",
            "best_ntree_limit": 477
        },
        {
            "library_version": "1.2.10",
            "algorithm_name": "CatBoost",
            "algorithm_short_name": "CatBoost",
            "uid": "3de8a043-4c65-4f5e-9d11-4979a85624f0",
            "params": {
                "model_type": "CatBoost",
                "ml_task": "regression",
                "n_jobs": -1,
                "seed": 43,
                "learning_rate": 0.1,
                "depth": 5,
                "rsm": 0.8,
                "loss_function": "RMSE",
                "eval_metric": "RMSE",
                "explain_level": 1
            },
            "name": "learner_fold_3",
            "best_ntree_limit": 432
        },
        {
            "library_version": "1.2.10",
            "algorithm_name": "CatBoost",
            "algorithm_short_name": "CatBoost",
            "uid": "9ced378c-539c-4650-87c6-cba6b1a15ac0",
            "params": {
                "model_type": "CatBoost",
                "ml_task": "regression",
                "n_jobs": -1,
                "seed": 43,
                "learning_rate": 0.1,
                "depth": 5,
                "rsm": 0.8,
                "loss_function": "RMSE",
                "eval_metric": "RMSE",
                "explain_level": 1
            },
            "name": "learner_fold_4",
            "best_ntree_limit": 389
        }
    ],
    "params": {
        "additional": {
            "max_rounds": 10000,
            "early_stopping_rounds": 50,
            "max_rows_limit": null,
            "max_cols_limit": null
        },
        "preprocessing": {
            "columns_preprocessing": {},
            "target_preprocessing": [
                "na_exclude",
                "scale_normal"
            ],
            "ml_task": "regression"
        },
        "validation_strategy": {
            "validation_type": "kfold",
            "k_folds": 5,
            "shuffle": true,
            "random_seed": 42,
            "X_path": "models/AutoML_Concrete_Strength/X.data",
            "y_path": "models/AutoML_Concrete_Strength/y.data",
            "results_path": "models/AutoML_Concrete_Strength"
        },
        "learner": {
            "model_type": "CatBoost",
            "ml_task": "regression",
            "n_jobs": -1,
            "seed": 43,
            "learning_rate": 0.1,
            "depth": 5,
            "rsm": 0.8,
            "loss_function": "RMSE",
            "eval_metric": "RMSE",
            "explain_level": 1
        },
        "automl_random_state": 42,
        "ml_task": "regression",
        "explain_level": 1,
        "name": "76_CatBoost",
        "status": "initialized",
        "final_loss": null,
        "train_time": null,
        "data_type": "original",
        "max_time_for_learner": 60
    },
    "saved": [
        "76_CatBoost/learner_fold_0.catboost",
        "76_CatBoost/learner_fold_1.catboost",
        "76_CatBoost/learner_fold_2.catboost",
        "76_CatBoost/learner_fold_3.catboost",
        "76_CatBoost/learner_fold_4.catboost"
    ],
    "predictions_fname": "76_CatBoost/predictions_out_of_folds.csv",
    "metric_name": "rmse",
    "final_loss": "4.648984221354525",
    "train_time": 5.851898908615112,
    "is_stacked": false,
    "joblib_version": "1.5.3"
}