{
    "uid": "e987d354-975b-4e61-bb2c-8a096954811c",
    "name": "15_Xgboost",
    "preprocessing": [
        {
            "scale_y": {
                "scale": [
                    16.065133797995042
                ],
                "mean": [
                    35.83677083333334
                ],
                "var": [
                    258.0885239474826
                ],
                "n_samples_seen": 576,
                "n_features_in": 1,
                "columns": [
                    "target"
                ],
                "scale_method": "scale_normal"
            },
            "ml_task": "regression",
            "params": {
                "columns_preprocessing": {},
                "target_preprocessing": [
                    "na_exclude",
                    "scale_normal"
                ],
                "ml_task": "regression"
            }
        },
        {
            "scale_y": {
                "scale": [
                    16.32467381921671
                ],
                "mean": [
                    35.732708333333335
                ],
                "var": [
                    266.49497530381944
                ],
                "n_samples_seen": 576,
                "n_features_in": 1,
                "columns": [
                    "target"
                ],
                "scale_method": "scale_normal"
            },
            "ml_task": "regression",
            "params": {
                "columns_preprocessing": {},
                "target_preprocessing": [
                    "na_exclude",
                    "scale_normal"
                ],
                "ml_task": "regression"
            }
        },
        {
            "scale_y": {
                "scale": [
                    16.846179028420384
                ],
                "mean": [
                    36.27475694444444
                ],
                "var": [
                    283.7937478575907
                ],
                "n_samples_seen": 576,
                "n_features_in": 1,
                "columns": [
                    "target"
                ],
                "scale_method": "scale_normal"
            },
            "ml_task": "regression",
            "params": {
                "columns_preprocessing": {},
                "target_preprocessing": [
                    "na_exclude",
                    "scale_normal"
                ],
                "ml_task": "regression"
            }
        },
        {
            "scale_y": {
                "scale": [
                    16.540091162165027
                ],
                "mean": [
                    35.93711805555555
                ],
                "var": [
                    273.57461565272956
                ],
                "n_samples_seen": 576,
                "n_features_in": 1,
                "columns": [
                    "target"
                ],
                "scale_method": "scale_normal"
            },
            "ml_task": "regression",
            "params": {
                "columns_preprocessing": {},
                "target_preprocessing": [
                    "na_exclude",
                    "scale_normal"
                ],
                "ml_task": "regression"
            }
        },
        {
            "scale_y": {
                "scale": [
                    16.59640991093148
                ],
                "mean": [
                    36.22142361111111
                ],
                "var": [
                    275.4408219316647
                ],
                "n_samples_seen": 576,
                "n_features_in": 1,
                "columns": [
                    "target"
                ],
                "scale_method": "scale_normal"
            },
            "ml_task": "regression",
            "params": {
                "columns_preprocessing": {},
                "target_preprocessing": [
                    "na_exclude",
                    "scale_normal"
                ],
                "ml_task": "regression"
            }
        }
    ],
    "learners": [
        {
            "library_version": "3.3.0",
            "algorithm_name": "Extreme Gradient Boosting",
            "algorithm_short_name": "Xgboost",
            "uid": "eaca7c7e-c47f-4ed3-926d-bd6e90f35b2f",
            "params": {
                "model_type": "Xgboost",
                "ml_task": "regression",
                "n_jobs": -1,
                "seed": 51,
                "objective": "reg:squarederror",
                "eta": 0.05,
                "max_depth": 6,
                "min_child_weight": 10,
                "subsample": 0.6,
                "colsample_bytree": 0.6,
                "eval_metric": "rmse",
                "explain_level": 1
            },
            "name": "learner_fold_0"
        },
        {
            "library_version": "3.3.0",
            "algorithm_name": "Extreme Gradient Boosting",
            "algorithm_short_name": "Xgboost",
            "uid": "c358d32d-cf23-4bcd-985b-598e276ce050",
            "params": {
                "model_type": "Xgboost",
                "ml_task": "regression",
                "n_jobs": -1,
                "seed": 51,
                "objective": "reg:squarederror",
                "eta": 0.05,
                "max_depth": 6,
                "min_child_weight": 10,
                "subsample": 0.6,
                "colsample_bytree": 0.6,
                "eval_metric": "rmse",
                "explain_level": 1
            },
            "name": "learner_fold_1"
        },
        {
            "library_version": "3.3.0",
            "algorithm_name": "Extreme Gradient Boosting",
            "algorithm_short_name": "Xgboost",
            "uid": "8a527ef4-4b59-4f28-abcf-bbd48d25e08b",
            "params": {
                "model_type": "Xgboost",
                "ml_task": "regression",
                "n_jobs": -1,
                "seed": 51,
                "objective": "reg:squarederror",
                "eta": 0.05,
                "max_depth": 6,
                "min_child_weight": 10,
                "subsample": 0.6,
                "colsample_bytree": 0.6,
                "eval_metric": "rmse",
                "explain_level": 1
            },
            "name": "learner_fold_2"
        },
        {
            "library_version": "3.3.0",
            "algorithm_name": "Extreme Gradient Boosting",
            "algorithm_short_name": "Xgboost",
            "uid": "5d6d7d2a-1262-4b63-a99e-92745bcd4907",
            "params": {
                "model_type": "Xgboost",
                "ml_task": "regression",
                "n_jobs": -1,
                "seed": 51,
                "objective": "reg:squarederror",
                "eta": 0.05,
                "max_depth": 6,
                "min_child_weight": 10,
                "subsample": 0.6,
                "colsample_bytree": 0.6,
                "eval_metric": "rmse",
                "explain_level": 1
            },
            "name": "learner_fold_3"
        },
        {
            "library_version": "3.3.0",
            "algorithm_name": "Extreme Gradient Boosting",
            "algorithm_short_name": "Xgboost",
            "uid": "bf0d2c97-d765-4110-967a-5c4b2a3f0700",
            "params": {
                "model_type": "Xgboost",
                "ml_task": "regression",
                "n_jobs": -1,
                "seed": 51,
                "objective": "reg:squarederror",
                "eta": 0.05,
                "max_depth": 6,
                "min_child_weight": 10,
                "subsample": 0.6,
                "colsample_bytree": 0.6,
                "eval_metric": "rmse",
                "explain_level": 1
            },
            "name": "learner_fold_4"
        }
    ],
    "params": {
        "additional": {
            "max_rounds": 10000,
            "early_stopping_rounds": 50,
            "max_rows_limit": null,
            "max_cols_limit": null
        },
        "preprocessing": {
            "columns_preprocessing": {},
            "target_preprocessing": [
                "na_exclude",
                "scale_normal"
            ],
            "ml_task": "regression"
        },
        "validation_strategy": {
            "validation_type": "kfold",
            "k_folds": 5,
            "shuffle": true,
            "random_seed": 42,
            "X_path": "models/AutoML_Concrete_Strength/X.data",
            "y_path": "models/AutoML_Concrete_Strength/y.data",
            "results_path": "models/AutoML_Concrete_Strength"
        },
        "learner": {
            "model_type": "Xgboost",
            "ml_task": "regression",
            "n_jobs": -1,
            "seed": 51,
            "objective": "reg:squarederror",
            "eta": 0.05,
            "max_depth": 6,
            "min_child_weight": 10,
            "subsample": 0.6,
            "colsample_bytree": 0.6,
            "eval_metric": "rmse",
            "explain_level": 1
        },
        "automl_random_state": 42,
        "ml_task": "regression",
        "explain_level": 1,
        "name": "15_Xgboost",
        "status": "initialized",
        "final_loss": null,
        "train_time": null,
        "data_type": "original",
        "max_time_for_learner": 60
    },
    "saved": [
        "15_Xgboost/learner_fold_0.xgboost.json",
        "15_Xgboost/learner_fold_1.xgboost.json",
        "15_Xgboost/learner_fold_2.xgboost.json",
        "15_Xgboost/learner_fold_3.xgboost.json",
        "15_Xgboost/learner_fold_4.xgboost.json"
    ],
    "predictions_fname": "15_Xgboost/predictions_out_of_folds.csv",
    "metric_name": "rmse",
    "final_loss": "4.616611628200106",
    "train_time": 7.911843776702881,
    "is_stacked": false,
    "joblib_version": "1.5.3"
}